setup.cfg
setup.py
ridi/cms/__init__.py
ridi/cms/cms_client.py
ridi/cms/config.py
ridi/cms/login_session.py
ridi/cms/thrift/AdminAuth/AdminAuthService.py
ridi/cms/thrift/AdminAuth/__init__.py
ridi/cms/thrift/AdminAuth/constants.py
ridi/cms/thrift/AdminAuth/ttypes.py
ridi/cms/thrift/AdminMenu/AdminMenuService.py
ridi/cms/thrift/AdminMenu/__init__.py
ridi/cms/thrift/AdminMenu/constants.py
ridi/cms/thrift/AdminMenu/ttypes.py
ridi/cms/thrift/AdminTag/AdminTagService.py
ridi/cms/thrift/AdminTag/__init__.py
ridi/cms/thrift/AdminTag/constants.py
ridi/cms/thrift/AdminTag/ttypes.py
ridi/cms/thrift/AdminUser/AdminUserService.py
ridi/cms/thrift/AdminUser/__init__.py
ridi/cms/thrift/AdminUser/constants.py
ridi/cms/thrift/AdminUser/ttypes.py
ridi/cms/thrift/Errors/__init__.py
ridi/cms/thrift/Errors/constants.py
ridi/cms/thrift/Errors/ttypes.py
ridi_cms_sdk.egg-info/PKG-INFO
ridi_cms_sdk.egg-info/SOURCES.txt
ridi_cms_sdk.egg-info/dependency_links.txt
ridi_cms_sdk.egg-info/requires.txt
ridi_cms_sdk.egg-info/top_level.txt
test/test_admin_auth.py