Metadata-Version: 1.1
Name: ridi-cms-sdk
Version: 2.2.6
Summary: Ridi CMS SDK
Home-page: https://github.com/ridi/cms-sdk
Author: UNKNOWN
Author-email: UNKNOWN
License: UNKNOWN
Keywords: cmssdk,ridi,ridibooks
Platform: UNKNOWN
Classifier: License :: OSI Approved :: MIT License
Classifier: Programming Language :: Python :: 3
